downrinth.py
downrinth-0.3.dist-info/METADATA
downrinth-0.3.dist-info/WHEEL
downrinth-0.3.dist-info/top_level.txt
downrinth-0.3.dist-info/RECORD
