Metadata-Version: 2.1
Name: downrinth
Version: 0.3
Summary: A Python utility to download mods from Modrinth.S
Author: Vihaan Pundir
Classifier: Programming Language :: Python :: 3
Classifier: License :: OSI Approved :: MIT License
Classifier: Operating System :: OS Independent
Requires-Python: >=3.6
